akamaihttp/__init__.py
akamaihttp/akamaihttp.py
akamaihttp-1.6.4.dist-info/LICENSE
akamaihttp-1.6.4.dist-info/METADATA
akamaihttp-1.6.4.dist-info/WHEEL
akamaihttp-1.6.4.dist-info/top_level.txt
akamaihttp-1.6.4.dist-info/RECORD
