Metadata-Version: 2.1
Name: akamaihttp
Version: 1.6.4
Summary: A Pip Package for Akamai HttpHandlder
Home-page: https://github.com/Achuthananda/AkamaiHTTPHandler
Author: Achuthananda M P
Author-email: achuthadivine@gmail.com
License: UNKNOWN
Platform: UNKNOWN
Classifier: Programming Language :: Python :: 3
Classifier: License :: OSI Approved :: MIT License
Classifier: Operating System :: OS Independent
Requires-Dist: edgegrid-python
Requires-Dist: requests
